tox_lambda_autodiscovery/__init__.py
tox_lambda_autodiscovery/plugin.py
tox_lambda_autodiscovery-0.1.6.dist-info/LICENSE
tox_lambda_autodiscovery-0.1.6.dist-info/METADATA
tox_lambda_autodiscovery-0.1.6.dist-info/WHEEL
tox_lambda_autodiscovery-0.1.6.dist-info/entry_points.txt
tox_lambda_autodiscovery-0.1.6.dist-info/top_level.txt
tox_lambda_autodiscovery-0.1.6.dist-info/RECORD
