Metadata-Version: 2.1
Name: tox-lambda-autodiscovery
Version: 0.1.6
Summary: autodiscovery and autocreate tox testenv to aws lambda function
Home-page: https://github.com/luzfcb/tox-lambda-autodiscovery
Author: Fabio C. Barrionuevo da Luz
Author-email: bnafta@gmail.com
Maintainer: Fabio C. Barrionuevo da Luz
Maintainer-email: bnafta@gmail.com
License: MIT
Platform: UNKNOWN
Classifier: Development Status :: 2 - Pre-Alpha
Classifier: Framework :: tox
Classifier: Intended Audience :: Developers
Classifier: Topic :: Software Development :: Testing
Classifier: Programming Language :: Python
Classifier: Programming Language :: Python :: 3.6
Classifier: Programming Language :: Python :: 3.7
Classifier: Programming Language :: Python :: Implementation :: CPython
Classifier: Operating System :: OS Independent
Classifier: License :: OSI Approved :: MIT License
Requires-Python: >=3.6, !=3.0.*, !=3.1.*, !=3.2.*, !=3.3.*
Requires-Dist: tox (>=3.3.0)
